LICENSE.txt
MANIFEST.in
README.md
setup.cfg
setup.py
harvest_api_client/__init__.py
harvest_api_client/harvest.py
harvest_api_client/tokens_manager.py
harvest_api_client.egg-info/PKG-INFO
harvest_api_client.egg-info/SOURCES.txt
harvest_api_client.egg-info/dependency_links.txt
harvest_api_client.egg-info/top_level.txt