Metadata-Version: 1.1
Name: harvest-api-client
Version: 1.1.3
Summary: A client for the Harvest API (getharvest.com)
Home-page: https://github.com/GildedHonour/harvest-api-client
Author: Alex Maslakov
Author-email: Alex Maslakov<me@gildedhonour.com>, Alex Maslakov<gilded.honour@gmail.com>
License: MIT
Keywords: harvest-api,api,harvest.com,getharvest.com,harvest,api client
Platform: UNKNOWN
Classifier: Development Status :: 5 - Production/Stable
Classifier: Intended Audience :: Developers
Classifier: Topic :: Software Development :: Libraries
Classifier: Topic :: Internet :: WWW/HTTP :: Site Management
Classifier: Topic :: Utilities
Classifier: License :: OSI Approved :: MIT License
Classifier: Programming Language :: Python :: 3.4
